codemetrics/__init__.py
codemetrics/cloc.py
codemetrics/cmdline.py
codemetrics/core.py
codemetrics/git.py
codemetrics/internals.py
codemetrics/lizardtokencounts.py
codemetrics/pbar.py
codemetrics/scm.py
codemetrics/svn.py
codemetrics/vega.py
codemetrics-1.0.0.dist-info/licenses/AUTHORS.rst
codemetrics-1.0.0.dist-info/licenses/LICENSE.txt
codemetrics-1.0.0.dist-info/METADATA
codemetrics-1.0.0.dist-info/WHEEL
codemetrics-1.0.0.dist-info/entry_points.txt
codemetrics-1.0.0.dist-info/top_level.txt
codemetrics-1.0.0.dist-info/RECORD
