Metadata-Version: 2.4
Name: codemetrics
Version: 1.0.0
Summary: SCM mining utility classes
Author-email: elmotec <elmotec@gmx.com>
License-Expression: MIT
Project-URL: Homepage, http://github.com/elmotec/codemetrics
Keywords: code,metrics,mining,scm,subversion,svn,Adam Tornhill,utilities
Classifier: Development Status :: 4 - Beta
Classifier: Environment :: Console
Classifier: Natural Language :: English
Classifier: Programming Language :: Python :: 3.10
Classifier: Programming Language :: Python :: 3.11
Classifier: Programming Language :: Python :: 3.12
Classifier: Programming Language :: Python :: 3.13
Classifier: Topic :: Software Development
Classifier: Topic :: Utilities
Classifier: Topic :: Software Development :: Version Control
Classifier: Intended Audience :: Developers
Classifier: Intended Audience :: Education
Requires-Python: >=3.6
License-File: LICENSE.txt
License-File: AUTHORS.rst
Requires-Dist: numpy>=2
Requires-Dist: click>=6
Requires-Dist: pandas>=2
Requires-Dist: tqdm>=4
Requires-Dist: python-dateutil>=2
Requires-Dist: scikit-learn
Requires-Dist: lizard>1.17
Requires-Dist: mypy-extensions
Provides-Extra: develop
Requires-Dist: black[d]; extra == "develop"
Requires-Dist: build; extra == "develop"
Requires-Dist: commitizen<4.9; extra == "develop"
Requires-Dist: coverage; extra == "develop"
Requires-Dist: flake8; extra == "develop"
Requires-Dist: pip; extra == "develop"
Requires-Dist: pre-commit; extra == "develop"
Requires-Dist: tox; extra == "develop"
Requires-Dist: twine; extra == "develop"
Requires-Dist: watchdog; extra == "develop"
Requires-Dist: wheel; extra == "develop"
Requires-Dist: pytest; extra == "develop"
Provides-Extra: notebooks
Requires-Dist: altair; extra == "notebooks"
Requires-Dist: ipywidgets; extra == "notebooks"
Requires-Dist: jupyterlab; extra == "notebooks"
Requires-Dist: matplotlib; extra == "notebooks"
Dynamic: license-file
